Flask_Pure-0.5.dist-info/DESCRIPTION.rst
Flask_Pure-0.5.dist-info/METADATA
Flask_Pure-0.5.dist-info/RECORD
Flask_Pure-0.5.dist-info/WHEEL
Flask_Pure-0.5.dist-info/metadata.json
Flask_Pure-0.5.dist-info/top_level.txt
flask_pure/__init__.py
flask_pure/static/grids-responsive-min.css
flask_pure/static/grids-responsive.css
flask_pure/static/pure-min.css
flask_pure/static/pure.css
flask_pure/templates/pure/layout.html
